cli/.flake8
cli/__init__.py
cli/__main__.py
cli/build.py
cli/commands/README.md
cli/commands/__init__.py
cli/commands/destroy.py
cli/commands/setup.py
cli/commands/workload/README.md
cli/commands/workload/__init__.py
cli/commands/workload/bootstrap.py
cli/commands/workload/create.py
cli/commands/workload/delete.py
cli/commands/workload/workload.py
cli/common/__init__.py
cli/common/const/__init__.py
cli/common/const/common_path.py
cli/common/const/const.py
cli/common/const/namespaces.py
cli/common/const/parameter_names.py
cli/common/custom_excpetions.py
cli/common/enums/__init__.py
cli/common/enums/cloud_providers.py
cli/common/enums/dns_registrars.py
cli/common/enums/gcp_resource_types.py
cli/common/enums/git_plans.py
cli/common/enums/git_providers.py
cli/common/enums/optional_services.py
cli/common/logging_config.py
cli/common/retry_decorator.py
cli/common/singleton_metaclass.py
cli/common/state_store.py
cli/common/tracing_decorator.py
cli/common/utils/__init__.py
cli/common/utils/command_utils.py
cli/common/utils/generators.py
cli/common/utils/k8s_utils.py
cli/common/utils/optional_services_manager.py
cli/common/utils/os_utils.py
cli/services/README.md
cli/services/__init__.py
cli/services/cloud/__init__.py
cli/services/cloud/aws/__init__.py
cli/services/cloud/aws/aws_manager.py
cli/services/cloud/aws/aws_sdk.py
cli/services/cloud/aws/aws_session_manager.py
cli/services/cloud/aws/iam_permissions.py
cli/services/cloud/azure/__init__.py
cli/services/cloud/azure/azure_manager.py
cli/services/cloud/azure/azure_sdk.py
cli/services/cloud/azure/iam_permissions.py
cli/services/cloud/cloud_provider_manager.py
cli/services/cloud/gcp/__init__.py
cli/services/cloud/gcp/gcp_manager.py
cli/services/cloud/gcp/gcp_sdk.py
cli/services/cloud/gcp/iam_permissions.py
cli/services/dependency_manager.py
cli/services/dns/__init__.py
cli/services/dns/azure_dns/__init__.py
cli/services/dns/azure_dns/azure_dns.py
cli/services/dns/dns_provider_manager.py
cli/services/dns/gcp_dns/__init__.py
cgdevxcli-0.6.0.dist-info/METADATA
cgdevxcli-0.6.0.dist-info/WHEEL
cgdevxcli-0.6.0.dist-info/entry_points.txt
cgdevxcli-0.6.0.dist-info/RECORD
