Metadata-Version: 2.1
Name: cgdevxcli
Version: 0.6.0
Summary: 
Author: Alexander Ulyanov
Author-email: alexu@cloudgeometry.io
Requires-Python: >=3.10,<3.13
Classifier: Programming Language :: Python :: 3
Classifier: Programming Language :: Python :: 3.10
Classifier: Programming Language :: Python :: 3.11
Classifier: Programming Language :: Python :: 3.12
Requires-Dist: PyInstaller (==5.13.2)
Requires-Dist: alive-progress (>=3.1.5,<4.0.0)
Requires-Dist: awscli (==1.29.56)
Requires-Dist: azure-identity (==1.14.0)
Requires-Dist: azure-mgmt-authorization (>=4.0.0,<5.0.0)
Requires-Dist: azure-mgmt-compute (>=30.5.0,<31.0.0)
Requires-Dist: azure-mgmt-containerservice (>=26.0.0,<27.0.0)
Requires-Dist: azure-mgmt-dns (>=8.1.0,<9.0.0)
Requires-Dist: azure-mgmt-privatedns (>=1.1.0,<2.0.0)
Requires-Dist: azure-mgmt-resource (==23.0.1)
Requires-Dist: azure-mgmt-storage (>=21.1.0,<22.0.0)
Requires-Dist: azure-mgmt-subscription (>=3.1.1,<4.0.0)
Requires-Dist: azure-storage-blob (==12.17.0)
Requires-Dist: boto3 (==1.28.56)
Requires-Dist: click (==8.1.7)
Requires-Dist: cloup (==3.0.2)
Requires-Dist: configparser (==6.0.0)
Requires-Dist: dnspython (==2.4.2)
Requires-Dist: gcloud (==0.18.3)
Requires-Dist: ghrepo (==0.7.0)
Requires-Dist: gitpython (==3.1.32)
Requires-Dist: google-api-python-client (>=2.121.0,<3.0.0)
Requires-Dist: google-auth (>=2.28.2,<3.0.0)
Requires-Dist: google-cloud-container (>=2.45.0,<3.0.0)
Requires-Dist: google-cloud-dns (>=0.35.0,<0.36.0)
Requires-Dist: google-cloud-storage (>=2.15.0,<3.0.0)
Requires-Dist: hvac (==1.2.1)
Requires-Dist: kr8s (>=0.17.0,<0.18.0)
Requires-Dist: kubernetes (==27.2.0)
Requires-Dist: pyyaml (==6.0.1)
Requires-Dist: setuptools (>=69.5.1,<70.0.0)
